pybsc/__init__.py
pybsc/audio_utils.py
pybsc/bytes_utils.py
pybsc/cache_readline_history.py
pybsc/cli.py
pybsc/clipboard_utils.py
pybsc/closest_indices.py
pybsc/colormap.py
pybsc/compress.py
pybsc/dict_utils.py
pybsc/download.py
pybsc/fastapi_utils.py
pybsc/get_target_ext.py
pybsc/git.py
pybsc/image_utils.py
pybsc/is_nan.py
pybsc/iter_utils.py
pybsc/json_utils.py
pybsc/make_fancy_output_dir.py
pybsc/makedirs.py
pybsc/md5sum_utils.py
pybsc/measure.py
pybsc/opener.py
pybsc/pickle_utils.py
pybsc/pycompat.py
pybsc/rm_utils.py
pybsc/run_many.py
pybsc/sort_utils.py
pybsc/split.py
pybsc/stdout_utils.py
pybsc/str_utils.py
pybsc/subprocess_utils.py
pybsc/tile.py
pybsc/time_str.py
pybsc/timestamp_utils.py
pybsc/video_utils.py
pybsc/warn_utils.py
pybsc/which.py
pybsc/yaml_utils.py
pybsc/apps/__init__.py
pybsc/apps/readable_json.py
pybsc/data/Roboto-Bold.ttf
pybsc/data/__init__.py
pybsc/heatmap/__init__.py
pybsc/heatmap/generate_heatmap.py
pybsc/imggen/__init__.py
pybsc/imggen/generate_texture.py
pybsc/imggen/top_n_color.py
pybsc/parallel/__init__.py
pybsc/parallel/parallel_tqdm.py
pybsc/ssh/__init__.py
pybsc/ssh/ssh_executor.py
pybsc/tts/__init__.py
pybsc/tts/azure_tts.py
pybsc/tts/azure_tts_voice.py
pybsc/tts/google_tts.py
pybsc/tts/google_tts_voice.py
pybsc/vision/__init__.py
pybsc/vision/blur_detection.py
pybsc/vision/color_filter.py
pybsc/visualizations/__init__.py
pybsc/visualizations/bbox.py
pybsc-0.1.69.dist-info/LICENSE
pybsc-0.1.69.dist-info/METADATA
pybsc-0.1.69.dist-info/WHEEL
pybsc-0.1.69.dist-info/entry_points.txt
pybsc-0.1.69.dist-info/top_level.txt
pybsc-0.1.69.dist-info/RECORD
